browserstacker/__init__$py.class
browserstacker/__init__.py
browserstacker/_compat$py.class
browserstacker/_compat.py
browserstacker/cli$py.class
browserstacker/constants.py
browserstacker/helpers$py.class
browserstacker/screenshots$py.class
browserstacker/screenshots.py
browserstacker/cli/__init__$py.class
browserstacker/cli/__init__.py
browserstacker/cli/helpers$py.class
browserstacker/cli/helpers.py
browserstacker-0.3.1.dist-info/DESCRIPTION.rst
browserstacker-0.3.1.dist-info/entry_points.txt
browserstacker-0.3.1.dist-info/METADATA
browserstacker-0.3.1.dist-info/metadata.json
browserstacker-0.3.1.dist-info/RECORD
browserstacker-0.3.1.dist-info/top_level.txt
browserstacker-0.3.1.dist-info/WHEEL
