Metadata-Version: 2.0
Name: browserstacker
Version: 0.3.1
Summary: Python wrapper for BrowserStack features.
Home-page: https://github.com/Stranger6667/browserstacker
Author: Dmitry Dygalo
Author-email: dadygalo@gmail.com
License: MIT
Keywords: browserstack,screenshots,testing
Platform: UNKNOWN
Classifier: Development Status :: 4 - Beta
Classifier: Environment :: Console
Classifier: Intended Audience :: Developers
Classifier: Operating System :: OS Independent
Classifier: License :: OSI Approved :: MIT License
Classifier: Programming Language :: Python
Classifier: Programming Language :: Python :: 2.6
Classifier: Programming Language :: Python :: 2.7
Classifier: Programming Language :: Python :: 3.2
Classifier: Programming Language :: Python :: 3.3
Classifier: Programming Language :: Python :: 3.4
Classifier: Programming Language :: Python :: 3.5
Classifier: Programming Language :: Python :: Implementation :: CPython
Classifier: Programming Language :: Python :: Implementation :: PyPy
Classifier: Programming Language :: Python :: Implementation :: Jython
Classifier: Topic :: Software Development :: Testing
Classifier: Topic :: Software Development :: User Interfaces
Requires-Dist: requests (>=2.9.0)
Requires-Dist: click (>=6.2)
